pct/__init__.py
pct/_modidx.py
pct/_nbdev.py
pct/applications.py
pct/arc.py
pct/architectures.py
pct/environment_processing.py
pct/environments.py
pct/errors.py
pct/experiments.py
pct/functions.py
pct/helpers.py
pct/hierarchy.py
pct/microgrid.py
pct/network.py
pct/nodes.py
pct/pctexamples.py
pct/plot.py
pct/plotarrays.py
pct/plotting.py
pct/putils.py
pct/structure.py
pct/webots.py
pct/yaw_module.py
pct-0.0.42.dist-info/licenses/LICENSE
pct-0.0.42.dist-info/METADATA
pct-0.0.42.dist-info/WHEEL
pct-0.0.42.dist-info/entry_points.txt
pct-0.0.42.dist-info/top_level.txt
pct-0.0.42.dist-info/RECORD
