Metadata-Version: 2.4
Name: pct
Version: 0.0.42
Summary: Perceptual Control Theory with Python
Home-page: https://github.com/perceptualrobots/pct/tree/master/
Author: Rupert Young
Author-email: rupert@perceptualrobots.com
License: Apache Software License 2.0
Keywords: pct,control systems,robotics,psychology
Classifier: Development Status :: 3 - Alpha
Classifier: Intended Audience :: Developers
Classifier: Natural Language :: English
Classifier: Programming Language :: Python :: 3.9
Classifier: Programming Language :: Python :: 3.10
Classifier: License :: OSI Approved :: Apache Software License
Requires-Python: >=3.9
License-File: LICENSE
Requires-Dist: numpy==1.23.5
Requires-Dist: pandas==1.5.3
Requires-Dist: ghapi
Requires-Dist: packaging
Requires-Dist: ipython
Requires-Dist: imageio
Requires-Dist: imageio-ffmpeg
Requires-Dist: drl_microgrid_ems
Requires-Dist: deprecated
Requires-Dist: pygame
Requires-Dist: plotly
Requires-Dist: matplotlib
Requires-Dist: scipy
Requires-Dist: gym
Requires-Dist: networkx
Requires-Dist: graphviz
Requires-Dist: jproperties
Requires-Dist: openpyxl
Requires-Dist: comet_ml
Provides-Extra: dev
Dynamic: author
Dynamic: author-email
Dynamic: classifier
Dynamic: description
Dynamic: description-content-type
Dynamic: home-page
Dynamic: keywords
Dynamic: license
Dynamic: license-file
Dynamic: provides-extra
Dynamic: requires-dist
Dynamic: requires-python
Dynamic: summary
